qadence_protocols/__init__.py
qadence_protocols/protocols.py
qadence_protocols/types.py
qadence_protocols/utils_trace.py
qadence_protocols/measurements/__init__.py
qadence_protocols/measurements/abstract.py
qadence_protocols/measurements/calibration.py
qadence_protocols/measurements/protocols.py
qadence_protocols/measurements/robust_shadow.py
qadence_protocols/measurements/shadow.py
qadence_protocols/measurements/tomography.py
qadence_protocols/measurements/utils_tomography.py
qadence_protocols/measurements/utils_shadow/__init__.py
qadence_protocols/measurements/utils_shadow/data_acquisition.py
qadence_protocols/measurements/utils_shadow/post_processing.py
qadence_protocols/measurements/utils_shadow/unitaries.py
qadence_protocols/mitigations/__init__.py
qadence_protocols/mitigations/analog_zne.py
qadence_protocols/mitigations/protocols.py
qadence_protocols/mitigations/readout.py
qadence_protocols/mitigations/twirl.py
qadence_protocols-0.2.1.dist-info/METADATA
qadence_protocols-0.2.1.dist-info/WHEEL
qadence_protocols-0.2.1.dist-info/licenses/LICENSE
qadence_protocols-0.2.1.dist-info/RECORD
