Metadata-Version: 2.4
Name: qadence-protocols
Version: 0.2.1
Summary: Protocols interface for running experiments using Qadence.
Author-email: Mario Dagrada <mario.dagrada@pasqal.com>, Roland Guichard <roland.guichard@pasqal.com>, Raja Selvarajan <raja.selvarajan@pasqal.com>, Gergana Velikova <gergana.velikova@pasqal.com>, Charles Moussa <charles.moussa@pasqal.com>
License: Apache 2.0
License-File: LICENSE
Keywords: quantum
Classifier: License :: OSI Approved :: Apache Software License
Classifier: Programming Language :: Python
Classifier: Programming Language :: Python :: 3
Classifier: Programming Language :: Python :: 3.9
Classifier: Programming Language :: Python :: 3.10
Classifier: Programming Language :: Python :: 3.11
Classifier: Programming Language :: Python :: Implementation :: CPython
Classifier: Programming Language :: Python :: Implementation :: PyPy
Requires-Python: <3.12,>=3.9
Requires-Dist: qadence[pulser]
Requires-Dist: torch
